pulsar_sdk_py/__init__.py
pulsar_sdk_py/constants.py
pulsar_sdk_py/dataclasses/__init__.py
pulsar_sdk_py/dataclasses/schemas.py
pulsar_sdk_py/dataclasses/serializer.py
pulsar_sdk_py/enums.py
pulsar_sdk_py/exceptions.py
pulsar_sdk_py/helpers.py
pulsar_sdk_py/logger.py
pulsar_sdk_py/pulsar_sdk.py
pulsar_sdk_py/rest/__init__.py
pulsar_sdk_py/rest/base.py
pulsar_sdk_py/rest/name_service.py
pulsar_sdk_py/rest/nfts.py
pulsar_sdk_py/rest/protocols.py
pulsar_sdk_py/rest/tokens.py
pulsar_sdk_py/rest/wallets.py
pulsar_sdk_py/sleep.py
pulsar_sdk_py/websocket/__init__.py
pulsar_sdk_py/websocket/balances.py
pulsar_sdk_py/websocket/base.py
pulsar_sdk_py/websocket/encryption.py
pulsar_sdk_py/websocket/websocket_types.py
pulsar_sdk_py-1.0.5.dist-info/METADATA
pulsar_sdk_py-1.0.5.dist-info/WHEEL
pulsar_sdk_py-1.0.5.dist-info/entry_points.txt
pulsar_sdk_py-1.0.5.dist-info/RECORD
