Metadata-Version: 2.1
Name: pulsar-sdk-py
Version: 1.0.5
Summary: 
Author: Pulsar
Author-email: admin@pulsar.finance
Requires-Python: >=3.10
Classifier: Programming Language :: Python :: 3
Classifier: Programming Language :: Python :: 3.10
Classifier: Programming Language :: Python :: 3.11
Classifier: Programming Language :: Python :: 3.12
Classifier: Programming Language :: Python :: 3.13
Requires-Dist: asyncio (>=3.4.3,<4.0.0)
Requires-Dist: cryptography (>=41.0.7,<42.0.0)
Requires-Dist: dacite (>=1.8.1,<2.0.0)
Requires-Dist: python-dotenv (>=1.0.1,<2.0.0)
Requires-Dist: requests (==2.31.0)
Requires-Dist: websockets (>=10.0,<11.0)
